{"species":"Apilactobacillus micheneri","superkingdom":"Bacteria","n_records":0,"n_mu":0,"n_phenotypes":3,"growth_records":[],"phenotypes":[{"substrate":"D-fructose","exchange":"EX_fru_e","category":"carbon","phenotype":"positive","n_strains":1,"n_positive":1,"n_negative":0,"sources":["bacdive"],"kinds":["builds acid from"],"citation":"BacDive strain 158413 (Reimer LC et al., BacDive 2022, NAR); https://bacdive.dsmz.de/strain/158413"},{"substrate":"D-glucose","exchange":"EX_glc__D_e","category":"carbon","phenotype":"positive","n_strains":1,"n_positive":1,"n_negative":0,"sources":["bacdive"],"kinds":["builds acid from"],"citation":"BacDive strain 158413 (Reimer LC et al., BacDive 2022, NAR); https://bacdive.dsmz.de/strain/158413"},{"substrate":"glucose","exchange":"EX_glc__D_e","category":"carbon","phenotype":"positive","n_strains":1,"n_positive":1,"n_negative":0,"sources":["bacdive"],"kinds":["fermentation"],"citation":"BacDive strain 158413 (Reimer LC et al., BacDive 2022, NAR); https://bacdive.dsmz.de/strain/158413"}]}