{"species":"Halopiger thermotolerans","superkingdom":"","n_records":0,"n_mu":0,"n_phenotypes":30,"growth_records":[],"phenotypes":[{"substrate":"casein","exchange":null,"category":"carbon","phenotype":"negative","n_strains":1,"n_positive":0,"n_negative":1,"sources":["bacdive"],"kinds":["hydrolysis"],"citation":"BacDive strain 133244 (Reimer LC et al., BacDive 2022, NAR); https://bacdive.dsmz.de/strain/133244"},{"substrate":"cellulose","exchange":null,"category":"carbon","phenotype":"negative","n_strains":1,"n_positive":0,"n_negative":1,"sources":["bacdive"],"kinds":["hydrolysis"],"citation":"BacDive strain 133244 (Reimer LC et al., BacDive 2022, NAR); https://bacdive.dsmz.de/strain/133244"},{"substrate":"chitin","exchange":null,"category":"carbon","phenotype":"negative","n_strains":1,"n_positive":0,"n_negative":1,"sources":["bacdive"],"kinds":["hydrolysis"],"citation":"BacDive strain 133244 (Reimer LC et al., BacDive 2022, NAR); https://bacdive.dsmz.de/strain/133244"},{"substrate":"D-sorbitol","exchange":"EX_sbt__D_e","category":"carbon","phenotype":"negative","n_strains":1,"n_positive":0,"n_negative":1,"sources":["bacdive"],"kinds":["carbon source"],"citation":"BacDive strain 133244 (Reimer LC et al., BacDive 2022, NAR); https://bacdive.dsmz.de/strain/133244"},{"substrate":"gelatin","exchange":null,"category":"carbon","phenotype":"negative","n_strains":1,"n_positive":0,"n_negative":1,"sources":["bacdive"],"kinds":["hydrolysis"],"citation":"BacDive strain 133244 (Reimer LC et al., BacDive 2022, NAR); https://bacdive.dsmz.de/strain/133244"},{"substrate":"mannan","exchange":null,"category":"carbon","phenotype":"negative","n_strains":1,"n_positive":0,"n_negative":1,"sources":["bacdive"],"kinds":["hydrolysis"],"citation":"BacDive strain 133244 (Reimer LC et al., BacDive 2022, NAR); https://bacdive.dsmz.de/strain/133244"},{"substrate":"sodium citrate","exchange":null,"category":"carbon","phenotype":"negative","n_strains":1,"n_positive":0,"n_negative":1,"sources":["bacdive"],"kinds":["carbon source"],"citation":"BacDive strain 133244 (Reimer LC et al., BacDive 2022, NAR); https://bacdive.dsmz.de/strain/133244"},{"substrate":"starch","exchange":null,"category":"carbon","phenotype":"negative","n_strains":1,"n_positive":0,"n_negative":1,"sources":["bacdive"],"kinds":["hydrolysis"],"citation":"BacDive strain 133244 (Reimer LC et al., BacDive 2022, NAR); https://bacdive.dsmz.de/strain/133244"},{"substrate":"tryptophan","exchange":"EX_trp__L_e","category":"carbon","phenotype":"negative","n_strains":1,"n_positive":0,"n_negative":1,"sources":["bacdive"],"kinds":["energy source"],"citation":"BacDive strain 133244 (Reimer LC et al., BacDive 2022, NAR); https://bacdive.dsmz.de/strain/133244"},{"substrate":"tween 80","exchange":null,"category":"carbon","phenotype":"negative","n_strains":1,"n_positive":0,"n_negative":1,"sources":["bacdive"],"kinds":["hydrolysis"],"citation":"BacDive strain 133244 (Reimer LC et al., BacDive 2022, NAR); https://bacdive.dsmz.de/strain/133244"},{"substrate":"D-galactose","exchange":"EX_gal_e","category":"carbon","phenotype":"positive","n_strains":1,"n_positive":1,"n_negative":0,"sources":["bacdive"],"kinds":["carbon source"],"citation":"BacDive strain 133244 (Reimer LC et al., BacDive 2022, NAR); https://bacdive.dsmz.de/strain/133244"},{"substrate":"D-glucose","exchange":"EX_glc__D_e","category":"carbon","phenotype":"positive","n_strains":1,"n_positive":1,"n_negative":0,"sources":["bacdive"],"kinds":["carbon source"],"citation":"BacDive strain 133244 (Reimer LC et al., BacDive 2022, NAR); https://bacdive.dsmz.de/strain/133244"},{"substrate":"disodium malate","exchange":null,"category":"carbon","phenotype":"positive","n_strains":1,"n_positive":1,"n_negative":0,"sources":["bacdive"],"kinds":["carbon source"],"citation":"BacDive strain 133244 (Reimer LC et al., BacDive 2022, NAR); https://bacdive.dsmz.de/strain/133244"},{"substrate":"glycerol","exchange":"EX_glyc_e","category":"carbon","phenotype":"positive","n_strains":1,"n_positive":1,"n_negative":0,"sources":["bacdive"],"kinds":["carbon source"],"citation":"BacDive strain 133244 (Reimer LC et al., BacDive 2022, NAR); https://bacdive.dsmz.de/strain/133244"},{"substrate":"nitrate","exchange":"EX_no3_e","category":"carbon","phenotype":"positive","n_strains":1,"n_positive":1,"n_negative":0,"sources":["bacdive"],"kinds":["reduction"],"citation":"BacDive strain 133244 (Reimer LC et al., BacDive 2022, NAR); https://bacdive.dsmz.de/strain/133244"},{"substrate":"sodium acetate","exchange":null,"category":"carbon","phenotype":"positive","n_strains":1,"n_positive":1,"n_negative":0,"sources":["bacdive"],"kinds":["carbon source"],"citation":"BacDive strain 133244 (Reimer LC et al., BacDive 2022, NAR); https://bacdive.dsmz.de/strain/133244"},{"substrate":"sodium L-glutamate","exchange":null,"category":"carbon","phenotype":"positive","n_strains":1,"n_positive":1,"n_negative":0,"sources":["bacdive"],"kinds":["carbon source"],"citation":"BacDive strain 133244 (Reimer LC et al., BacDive 2022, NAR); https://bacdive.dsmz.de/strain/133244"},{"substrate":"sodium pyruvate","exchange":null,"category":"carbon","phenotype":"positive","n_strains":1,"n_positive":1,"n_negative":0,"sources":["bacdive"],"kinds":["carbon source"],"citation":"BacDive strain 133244 (Reimer LC et al., BacDive 2022, NAR); https://bacdive.dsmz.de/strain/133244"},{"substrate":"sodium succinate","exchange":null,"category":"carbon","phenotype":"positive","n_strains":1,"n_positive":1,"n_negative":0,"sources":["bacdive"],"kinds":["carbon source"],"citation":"BacDive strain 133244 (Reimer LC et al., BacDive 2022, NAR); https://bacdive.dsmz.de/strain/133244"},{"substrate":"D-fructose","exchange":"EX_fru_e","category":"carbon","phenotype":"variable","n_strains":1,"n_positive":0,"n_negative":0,"sources":["bacdive"],"kinds":["carbon source"],"citation":"BacDive strain 133244 (Reimer LC et al., BacDive 2022, NAR); https://bacdive.dsmz.de/strain/133244"},{"substrate":"lactose","exchange":null,"category":"carbon","phenotype":"variable","n_strains":1,"n_positive":0,"n_negative":0,"sources":["bacdive"],"kinds":["carbon source"],"citation":"BacDive strain 133244 (Reimer LC et al., BacDive 2022, NAR); https://bacdive.dsmz.de/strain/133244"},{"substrate":"D-mannitol","exchange":"EX_mnl_e","category":"carbon","phenotype":"variable","n_strains":1,"n_positive":0,"n_negative":0,"sources":["bacdive"],"kinds":["carbon source"],"citation":"BacDive strain 133244 (Reimer LC et al., BacDive 2022, NAR); https://bacdive.dsmz.de/strain/133244"},{"substrate":"D-mannose","exchange":"EX_man_e","category":"carbon","phenotype":"variable","n_strains":1,"n_positive":0,"n_negative":0,"sources":["bacdive"],"kinds":["carbon source"],"citation":"BacDive strain 133244 (Reimer LC et al., BacDive 2022, NAR); https://bacdive.dsmz.de/strain/133244"},{"substrate":"D-xylose","exchange":"EX_xyl__D_e","category":"carbon","phenotype":"variable","n_strains":1,"n_positive":0,"n_negative":0,"sources":["bacdive"],"kinds":["carbon source"],"citation":"BacDive strain 133244 (Reimer LC et al., BacDive 2022, NAR); https://bacdive.dsmz.de/strain/133244"},{"substrate":"disodium fumarate","exchange":null,"category":"carbon","phenotype":"variable","n_strains":1,"n_positive":0,"n_negative":0,"sources":["bacdive"],"kinds":["carbon source"],"citation":"BacDive strain 133244 (Reimer LC et al., BacDive 2022, NAR); https://bacdive.dsmz.de/strain/133244"},{"substrate":"L-rhamnose","exchange":"EX_rmn_e","category":"carbon","phenotype":"variable","n_strains":1,"n_positive":0,"n_negative":0,"sources":["bacdive"],"kinds":["carbon source"],"citation":"BacDive strain 133244 (Reimer LC et al., BacDive 2022, NAR); https://bacdive.dsmz.de/strain/133244"},{"substrate":"maltose","exchange":null,"category":"carbon","phenotype":"variable","n_strains":1,"n_positive":0,"n_negative":0,"sources":["bacdive"],"kinds":["carbon source"],"citation":"BacDive strain 133244 (Reimer LC et al., BacDive 2022, NAR); https://bacdive.dsmz.de/strain/133244"},{"substrate":"ribose","exchange":"EX_rib__D_e","category":"carbon","phenotype":"variable","n_strains":1,"n_positive":0,"n_negative":0,"sources":["bacdive"],"kinds":["carbon source"],"citation":"BacDive strain 133244 (Reimer LC et al., BacDive 2022, NAR); https://bacdive.dsmz.de/strain/133244"},{"substrate":"sodium propionate","exchange":null,"category":"carbon","phenotype":"variable","n_strains":1,"n_positive":0,"n_negative":0,"sources":["bacdive"],"kinds":["carbon source"],"citation":"BacDive strain 133244 (Reimer LC et al., BacDive 2022, NAR); https://bacdive.dsmz.de/strain/133244"},{"substrate":"sucrose","exchange":null,"category":"carbon","phenotype":"variable","n_strains":1,"n_positive":0,"n_negative":0,"sources":["bacdive"],"kinds":["carbon source"],"citation":"BacDive strain 133244 (Reimer LC et al., BacDive 2022, NAR); https://bacdive.dsmz.de/strain/133244"}]}