{"species":"Hyphococcus flavus","superkingdom":"Bacteria","n_records":0,"n_mu":0,"n_phenotypes":42,"growth_records":[],"phenotypes":[{"substrate":"glucose","exchange":"EX_glc__D_e","category":"carbon","phenotype":"negative","n_strains":1,"n_positive":0,"n_negative":1,"sources":["bacdive"],"kinds":["fermentation"],"citation":"BacDive strain 140765 (Reimer LC et al., BacDive 2022, NAR); https://bacdive.dsmz.de/strain/140765"},{"substrate":"alginate","exchange":null,"category":"carbon","phenotype":"negative","n_strains":1,"n_positive":0,"n_negative":1,"sources":["bacdive"],"kinds":["hydrolysis"],"citation":"BacDive strain 140765 (Reimer LC et al., BacDive 2022, NAR); https://bacdive.dsmz.de/strain/140765"},{"substrate":"casein","exchange":null,"category":"carbon","phenotype":"negative","n_strains":1,"n_positive":0,"n_negative":1,"sources":["bacdive"],"kinds":["hydrolysis"],"citation":"BacDive strain 140765 (Reimer LC et al., BacDive 2022, NAR); https://bacdive.dsmz.de/strain/140765"},{"substrate":"esculin","exchange":"EX_escul_e","category":"carbon","phenotype":"negative","n_strains":1,"n_positive":0,"n_negative":1,"sources":["bacdive"],"kinds":["hydrolysis"],"citation":"BacDive strain 140765 (Reimer LC et al., BacDive 2022, NAR); https://bacdive.dsmz.de/strain/140765"},{"substrate":"starch","exchange":null,"category":"carbon","phenotype":"negative","n_strains":1,"n_positive":0,"n_negative":1,"sources":["bacdive"],"kinds":["hydrolysis"],"citation":"BacDive strain 140765 (Reimer LC et al., BacDive 2022, NAR); https://bacdive.dsmz.de/strain/140765"},{"substrate":"tween 60","exchange":null,"category":"carbon","phenotype":"negative","n_strains":1,"n_positive":0,"n_negative":1,"sources":["bacdive"],"kinds":["hydrolysis"],"citation":"BacDive strain 140765 (Reimer LC et al., BacDive 2022, NAR); https://bacdive.dsmz.de/strain/140765"},{"substrate":"urea","exchange":"EX_urea_e","category":"carbon","phenotype":"negative","n_strains":1,"n_positive":0,"n_negative":1,"sources":["bacdive"],"kinds":["hydrolysis"],"citation":"BacDive strain 140765 (Reimer LC et al., BacDive 2022, NAR); https://bacdive.dsmz.de/strain/140765"},{"substrate":"nitrate","exchange":"EX_no3_e","category":"carbon","phenotype":"negative","n_strains":1,"n_positive":0,"n_negative":1,"sources":["bacdive"],"kinds":["reduction"],"citation":"BacDive strain 140765 (Reimer LC et al., BacDive 2022, NAR); https://bacdive.dsmz.de/strain/140765"},{"substrate":"gelatin","exchange":null,"category":"carbon","phenotype":"positive","n_strains":1,"n_positive":1,"n_negative":0,"sources":["bacdive"],"kinds":["hydrolysis"],"citation":"BacDive strain 140765 (Reimer LC et al., BacDive 2022, NAR); https://bacdive.dsmz.de/strain/140765"},{"substrate":"L-tyrosine","exchange":"EX_tyr__L_e","category":"carbon","phenotype":"positive","n_strains":1,"n_positive":1,"n_negative":0,"sources":["bacdive"],"kinds":["hydrolysis"],"citation":"BacDive strain 140765 (Reimer LC et al., BacDive 2022, NAR); https://bacdive.dsmz.de/strain/140765"},{"substrate":"tween 20","exchange":null,"category":"carbon","phenotype":"positive","n_strains":1,"n_positive":1,"n_negative":0,"sources":["bacdive"],"kinds":["hydrolysis"],"citation":"BacDive strain 140765 (Reimer LC et al., BacDive 2022, NAR); https://bacdive.dsmz.de/strain/140765"},{"substrate":"tween 40","exchange":null,"category":"carbon","phenotype":"positive","n_strains":2,"n_positive":2,"n_negative":0,"sources":["bacdive"],"kinds":["hydrolysis","respiration"],"citation":"BacDive strain 140765 (Reimer LC et al., BacDive 2022, NAR); https://bacdive.dsmz.de/strain/140765"},{"substrate":"tween 80","exchange":null,"category":"carbon","phenotype":"positive","n_strains":1,"n_positive":1,"n_negative":0,"sources":["bacdive"],"kinds":["hydrolysis"],"citation":"BacDive strain 140765 (Reimer LC et al., BacDive 2022, NAR); https://bacdive.dsmz.de/strain/140765"},{"substrate":"ribitol","exchange":"EX_rbt_e","category":"carbon","phenotype":"positive","n_strains":1,"n_positive":1,"n_negative":0,"sources":["bacdive"],"kinds":["respiration"],"citation":"BacDive strain 140765 (Reimer LC et al., BacDive 2022, NAR); https://bacdive.dsmz.de/strain/140765"},{"substrate":"alpha-cyclodextrin","exchange":null,"category":"carbon","phenotype":"positive","n_strains":1,"n_positive":1,"n_negative":0,"sources":["bacdive"],"kinds":["respiration"],"citation":"BacDive strain 140765 (Reimer LC et al., BacDive 2022, NAR); https://bacdive.dsmz.de/strain/140765"},{"substrate":"D-alanine","exchange":"EX_ala__L_e","category":"carbon","phenotype":"positive","n_strains":1,"n_positive":1,"n_negative":0,"sources":["bacdive"],"kinds":["respiration"],"citation":"BacDive strain 140765 (Reimer LC et al., BacDive 2022, NAR); https://bacdive.dsmz.de/strain/140765"},{"substrate":"D-glucuronate","exchange":"EX_glcur_e","category":"carbon","phenotype":"positive","n_strains":1,"n_positive":1,"n_negative":0,"sources":["bacdive"],"kinds":["respiration"],"citation":"BacDive strain 140765 (Reimer LC et al., BacDive 2022, NAR); https://bacdive.dsmz.de/strain/140765"},{"substrate":"D-mannitol","exchange":"EX_mnl_e","category":"carbon","phenotype":"positive","n_strains":1,"n_positive":1,"n_negative":0,"sources":["bacdive"],"kinds":["respiration"],"citation":"BacDive strain 140765 (Reimer LC et al., BacDive 2022, NAR); https://bacdive.dsmz.de/strain/140765"},{"substrate":"D-sorbitol","exchange":"EX_sbt__D_e","category":"carbon","phenotype":"positive","n_strains":1,"n_positive":1,"n_negative":0,"sources":["bacdive"],"kinds":["respiration"],"citation":"BacDive strain 140765 (Reimer LC et al., BacDive 2022, NAR); https://bacdive.dsmz.de/strain/140765"},{"substrate":"formate","exchange":"EX_for_e","category":"carbon","phenotype":"positive","n_strains":1,"n_positive":1,"n_negative":0,"sources":["bacdive"],"kinds":["respiration"],"citation":"BacDive strain 140765 (Reimer LC et al., BacDive 2022, NAR); https://bacdive.dsmz.de/strain/140765"},{"substrate":"glycyl L-aspartic acid","exchange":null,"category":"carbon","phenotype":"positive","n_strains":1,"n_positive":1,"n_negative":0,"sources":["bacdive"],"kinds":["respiration"],"citation":"BacDive strain 140765 (Reimer LC et al., BacDive 2022, NAR); https://bacdive.dsmz.de/strain/140765"},{"substrate":"hydroxyproline","exchange":null,"category":"carbon","phenotype":"positive","n_strains":1,"n_positive":1,"n_negative":0,"sources":["bacdive"],"kinds":["respiration"],"citation":"BacDive strain 140765 (Reimer LC et al., BacDive 2022, NAR); https://bacdive.dsmz.de/strain/140765"},{"substrate":"inosine","exchange":"EX_ins_e","category":"carbon","phenotype":"positive","n_strains":1,"n_positive":1,"n_negative":0,"sources":["bacdive"],"kinds":["respiration"],"citation":"BacDive strain 140765 (Reimer LC et al., BacDive 2022, NAR); https://bacdive.dsmz.de/strain/140765"},{"substrate":"L-alaninamide","exchange":null,"category":"carbon","phenotype":"positive","n_strains":1,"n_positive":1,"n_negative":0,"sources":["bacdive"],"kinds":["respiration"],"citation":"BacDive strain 140765 (Reimer LC et al., BacDive 2022, NAR); https://bacdive.dsmz.de/strain/140765"},{"substrate":"L-asparagine","exchange":"EX_asn__L_e","category":"carbon","phenotype":"positive","n_strains":1,"n_positive":1,"n_negative":0,"sources":["bacdive"],"kinds":["respiration"],"citation":"BacDive strain 140765 (Reimer LC et al., BacDive 2022, NAR); https://bacdive.dsmz.de/strain/140765"},{"substrate":"L-fucose","exchange":"EX_fuc__L_e","category":"carbon","phenotype":"positive","n_strains":1,"n_positive":1,"n_negative":0,"sources":["bacdive"],"kinds":["respiration"],"citation":"BacDive strain 140765 (Reimer LC et al., BacDive 2022, NAR); https://bacdive.dsmz.de/strain/140765"},{"substrate":"L-histidine","exchange":"EX_his__L_e","category":"carbon","phenotype":"positive","n_strains":1,"n_positive":1,"n_negative":0,"sources":["bacdive"],"kinds":["respiration"],"citation":"BacDive strain 140765 (Reimer LC et al., BacDive 2022, NAR); https://bacdive.dsmz.de/strain/140765"},{"substrate":"L-ornithine","exchange":"EX_orn__D_e","category":"carbon","phenotype":"positive","n_strains":1,"n_positive":1,"n_negative":0,"sources":["bacdive"],"kinds":["respiration"],"citation":"BacDive strain 140765 (Reimer LC et al., BacDive 2022, NAR); https://bacdive.dsmz.de/strain/140765"},{"substrate":"L-proline","exchange":"EX_pro__L_e","category":"carbon","phenotype":"positive","n_strains":1,"n_positive":1,"n_negative":0,"sources":["bacdive"],"kinds":["respiration"],"citation":"BacDive strain 140765 (Reimer LC et al., BacDive 2022, NAR); https://bacdive.dsmz.de/strain/140765"},{"substrate":"L-pyroglutamic acid","exchange":null,"category":"carbon","phenotype":"positive","n_strains":1,"n_positive":1,"n_negative":0,"sources":["bacdive"],"kinds":["respiration"],"citation":"BacDive strain 140765 (Reimer LC et al., BacDive 2022, NAR); https://bacdive.dsmz.de/strain/140765"},{"substrate":"L-rhamnose","exchange":"EX_rmn_e","category":"carbon","phenotype":"positive","n_strains":1,"n_positive":1,"n_negative":0,"sources":["bacdive"],"kinds":["respiration"],"citation":"BacDive strain 140765 (Reimer LC et al., BacDive 2022, NAR); https://bacdive.dsmz.de/strain/140765"},{"substrate":"L-threonine","exchange":"EX_thr__L_e","category":"carbon","phenotype":"positive","n_strains":1,"n_positive":1,"n_negative":0,"sources":["bacdive"],"kinds":["respiration"],"citation":"BacDive strain 140765 (Reimer LC et al., BacDive 2022, NAR); https://bacdive.dsmz.de/strain/140765"},{"substrate":"lactose","exchange":null,"category":"carbon","phenotype":"positive","n_strains":1,"n_positive":1,"n_negative":0,"sources":["bacdive"],"kinds":["respiration"],"citation":"BacDive strain 140765 (Reimer LC et al., BacDive 2022, NAR); https://bacdive.dsmz.de/strain/140765"},{"substrate":"melibiose","exchange":null,"category":"carbon","phenotype":"positive","n_strains":1,"n_positive":1,"n_negative":0,"sources":["bacdive"],"kinds":["respiration"],"citation":"BacDive strain 140765 (Reimer LC et al., BacDive 2022, NAR); https://bacdive.dsmz.de/strain/140765"},{"substrate":"monomethyl succinate","exchange":null,"category":"carbon","phenotype":"positive","n_strains":1,"n_positive":1,"n_negative":0,"sources":["bacdive"],"kinds":["respiration"],"citation":"BacDive strain 140765 (Reimer LC et al., BacDive 2022, NAR); https://bacdive.dsmz.de/strain/140765"},{"substrate":"N-acetylgalactosamine","exchange":null,"category":"carbon","phenotype":"positive","n_strains":1,"n_positive":1,"n_negative":0,"sources":["bacdive"],"kinds":["respiration"],"citation":"BacDive strain 140765 (Reimer LC et al., BacDive 2022, NAR); https://bacdive.dsmz.de/strain/140765"},{"substrate":"glycyl-l-glutamate","exchange":null,"category":"carbon","phenotype":"positive","n_strains":1,"n_positive":1,"n_negative":0,"sources":["bacdive"],"kinds":["respiration"],"citation":"BacDive strain 140765 (Reimer LC et al., BacDive 2022, NAR); https://bacdive.dsmz.de/strain/140765"},{"substrate":"raffinose","exchange":null,"category":"carbon","phenotype":"positive","n_strains":1,"n_positive":1,"n_negative":0,"sources":["bacdive"],"kinds":["respiration"],"citation":"BacDive strain 140765 (Reimer LC et al., BacDive 2022, NAR); https://bacdive.dsmz.de/strain/140765"},{"substrate":"sucrose","exchange":null,"category":"carbon","phenotype":"positive","n_strains":1,"n_positive":1,"n_negative":0,"sources":["bacdive"],"kinds":["respiration"],"citation":"BacDive strain 140765 (Reimer LC et al., BacDive 2022, NAR); https://bacdive.dsmz.de/strain/140765"},{"substrate":"turanose","exchange":null,"category":"carbon","phenotype":"positive","n_strains":1,"n_positive":1,"n_negative":0,"sources":["bacdive"],"kinds":["respiration"],"citation":"BacDive strain 140765 (Reimer LC et al., BacDive 2022, NAR); https://bacdive.dsmz.de/strain/140765"},{"substrate":"uridine","exchange":"EX_uri_e","category":"carbon","phenotype":"positive","n_strains":1,"n_positive":1,"n_negative":0,"sources":["bacdive"],"kinds":["respiration"],"citation":"BacDive strain 140765 (Reimer LC et al., BacDive 2022, NAR); https://bacdive.dsmz.de/strain/140765"},{"substrate":"xylitol","exchange":null,"category":"carbon","phenotype":"positive","n_strains":1,"n_positive":1,"n_negative":0,"sources":["bacdive"],"kinds":["respiration"],"citation":"BacDive strain 140765 (Reimer LC et al., BacDive 2022, NAR); https://bacdive.dsmz.de/strain/140765"}]}