{"species":"Kibdelosporangium metalli","superkingdom":"","n_records":0,"n_mu":0,"n_phenotypes":46,"growth_records":[],"phenotypes":[{"substrate":"dextrin","exchange":null,"category":"carbon","phenotype":"negative","n_strains":2,"n_positive":0,"n_negative":2,"sources":["bacdive"],"kinds":["builds acid from","carbon source"],"citation":"BacDive strain 133307 (Reimer LC et al., BacDive 2022, NAR); https://bacdive.dsmz.de/strain/133307"},{"substrate":"erythritol","exchange":null,"category":"carbon","phenotype":"negative","n_strains":2,"n_positive":0,"n_negative":2,"sources":["bacdive"],"kinds":["builds acid from","carbon source"],"citation":"BacDive strain 133307 (Reimer LC et al., BacDive 2022, NAR); https://bacdive.dsmz.de/strain/133307"},{"substrate":"gelatin","exchange":null,"category":"carbon","phenotype":"negative","n_strains":1,"n_positive":0,"n_negative":1,"sources":["bacdive"],"kinds":["hydrolysis"],"citation":"BacDive strain 133307 (Reimer LC et al., BacDive 2022, NAR); https://bacdive.dsmz.de/strain/133307"},{"substrate":"L-histidine","exchange":"EX_his__L_e","category":"carbon","phenotype":"negative","n_strains":1,"n_positive":0,"n_negative":1,"sources":["bacdive"],"kinds":["degradation"],"citation":"BacDive strain 133307 (Reimer LC et al., BacDive 2022, NAR); https://bacdive.dsmz.de/strain/133307"},{"substrate":"L-rhamnose","exchange":"EX_rmn_e","category":"carbon","phenotype":"negative","n_strains":2,"n_positive":0,"n_negative":2,"sources":["bacdive"],"kinds":["builds acid from","carbon source"],"citation":"BacDive strain 133307 (Reimer LC et al., BacDive 2022, NAR); https://bacdive.dsmz.de/strain/133307"},{"substrate":"malate","exchange":"EX_mal__D_e","category":"carbon","phenotype":"variable","n_strains":2,"n_positive":1,"n_negative":1,"sources":["bacdive"],"kinds":["builds acid from","carbon source"],"citation":"BacDive strain 133307 (Reimer LC et al., BacDive 2022, NAR); https://bacdive.dsmz.de/strain/133307"},{"substrate":"nitrate","exchange":"EX_no3_e","category":"carbon","phenotype":"negative","n_strains":1,"n_positive":0,"n_negative":1,"sources":["bacdive"],"kinds":["reduction"],"citation":"BacDive strain 133307 (Reimer LC et al., BacDive 2022, NAR); https://bacdive.dsmz.de/strain/133307"},{"substrate":"raffinose","exchange":null,"category":"carbon","phenotype":"variable","n_strains":2,"n_positive":1,"n_negative":1,"sources":["bacdive"],"kinds":["builds acid from","carbon source"],"citation":"BacDive strain 133307 (Reimer LC et al., BacDive 2022, NAR); https://bacdive.dsmz.de/strain/133307"},{"substrate":"sodium citrate","exchange":null,"category":"carbon","phenotype":"negative","n_strains":2,"n_positive":0,"n_negative":2,"sources":["bacdive"],"kinds":["builds acid from","carbon source"],"citation":"BacDive strain 133307 (Reimer LC et al., BacDive 2022, NAR); https://bacdive.dsmz.de/strain/133307"},{"substrate":"sodium pyruvate","exchange":null,"category":"carbon","phenotype":"variable","n_strains":2,"n_positive":1,"n_negative":1,"sources":["bacdive"],"kinds":["builds acid from","carbon source"],"citation":"BacDive strain 133307 (Reimer LC et al., BacDive 2022, NAR); https://bacdive.dsmz.de/strain/133307"},{"substrate":"sodium succinate","exchange":null,"category":"carbon","phenotype":"variable","n_strains":2,"n_positive":1,"n_negative":1,"sources":["bacdive"],"kinds":["builds acid from","carbon source"],"citation":"BacDive strain 133307 (Reimer LC et al., BacDive 2022, NAR); https://bacdive.dsmz.de/strain/133307"},{"substrate":"sorbitol","exchange":"EX_sbt__D_e","category":"carbon","phenotype":"negative","n_strains":2,"n_positive":0,"n_negative":2,"sources":["bacdive"],"kinds":["builds acid from","carbon source"],"citation":"BacDive strain 133307 (Reimer LC et al., BacDive 2022, NAR); https://bacdive.dsmz.de/strain/133307"},{"substrate":"sorbose","exchange":null,"category":"carbon","phenotype":"negative","n_strains":2,"n_positive":0,"n_negative":1,"sources":["bacdive"],"kinds":["builds acid from","carbon source"],"citation":"BacDive strain 133307 (Reimer LC et al., BacDive 2022, NAR); https://bacdive.dsmz.de/strain/133307"},{"substrate":"xylitol","exchange":null,"category":"carbon","phenotype":"negative","n_strains":2,"n_positive":0,"n_negative":2,"sources":["bacdive"],"kinds":["builds acid from","carbon source"],"citation":"BacDive strain 133307 (Reimer LC et al., BacDive 2022, NAR); https://bacdive.dsmz.de/strain/133307"},{"substrate":"cellobiose","exchange":"EX_cellb_e","category":"carbon","phenotype":"positive","n_strains":2,"n_positive":2,"n_negative":0,"sources":["bacdive"],"kinds":["builds acid from","carbon source"],"citation":"BacDive strain 133307 (Reimer LC et al., BacDive 2022, NAR); https://bacdive.dsmz.de/strain/133307"},{"substrate":"D-arabinose","exchange":"EX_arab__L_e","category":"carbon","phenotype":"positive","n_strains":2,"n_positive":2,"n_negative":0,"sources":["bacdive"],"kinds":["builds acid from","carbon source"],"citation":"BacDive strain 133307 (Reimer LC et al., BacDive 2022, NAR); https://bacdive.dsmz.de/strain/133307"},{"substrate":"D-galactose","exchange":"EX_gal_e","category":"carbon","phenotype":"positive","n_strains":1,"n_positive":1,"n_negative":0,"sources":["bacdive"],"kinds":["builds acid from"],"citation":"BacDive strain 133307 (Reimer LC et al., BacDive 2022, NAR); https://bacdive.dsmz.de/strain/133307"},{"substrate":"fructose","exchange":"EX_fru_e","category":"carbon","phenotype":"positive","n_strains":2,"n_positive":2,"n_negative":0,"sources":["bacdive"],"kinds":["builds acid from","carbon source"],"citation":"BacDive strain 133307 (Reimer LC et al., BacDive 2022, NAR); https://bacdive.dsmz.de/strain/133307"},{"substrate":"fucose","exchange":"EX_fuc__L_e","category":"carbon","phenotype":"positive","n_strains":2,"n_positive":2,"n_negative":0,"sources":["bacdive"],"kinds":["builds acid from","carbon source"],"citation":"BacDive strain 133307 (Reimer LC et al., BacDive 2022, NAR); https://bacdive.dsmz.de/strain/133307"},{"substrate":"galactose","exchange":"EX_gal_e","category":"carbon","phenotype":"positive","n_strains":1,"n_positive":1,"n_negative":0,"sources":["bacdive"],"kinds":["carbon source"],"citation":"BacDive strain 133307 (Reimer LC et al., BacDive 2022, NAR); https://bacdive.dsmz.de/strain/133307"},{"substrate":"glucose","exchange":"EX_glc__D_e","category":"carbon","phenotype":"positive","n_strains":2,"n_positive":2,"n_negative":0,"sources":["bacdive"],"kinds":["builds acid from","carbon source"],"citation":"BacDive strain 133307 (Reimer LC et al., BacDive 2022, NAR); https://bacdive.dsmz.de/strain/133307"},{"substrate":"glycerol","exchange":"EX_glyc_e","category":"carbon","phenotype":"positive","n_strains":2,"n_positive":2,"n_negative":0,"sources":["bacdive"],"kinds":["builds acid from","carbon source"],"citation":"BacDive strain 133307 (Reimer LC et al., BacDive 2022, NAR); https://bacdive.dsmz.de/strain/133307"},{"substrate":"hypoxanthine","exchange":"EX_hxan_e","category":"carbon","phenotype":"positive","n_strains":1,"n_positive":1,"n_negative":0,"sources":["bacdive"],"kinds":["degradation"],"citation":"BacDive strain 133307 (Reimer LC et al., BacDive 2022, NAR); https://bacdive.dsmz.de/strain/133307"},{"substrate":"myo-inositol","exchange":"EX_inost_e","category":"carbon","phenotype":"positive","n_strains":2,"n_positive":2,"n_negative":0,"sources":["bacdive"],"kinds":["builds acid from","carbon source"],"citation":"BacDive strain 133307 (Reimer LC et al., BacDive 2022, NAR); https://bacdive.dsmz.de/strain/133307"},{"substrate":"L-alanine","exchange":"EX_ala__L_e","category":"carbon","phenotype":"positive","n_strains":1,"n_positive":1,"n_negative":0,"sources":["bacdive"],"kinds":["degradation"],"citation":"BacDive strain 133307 (Reimer LC et al., BacDive 2022, NAR); https://bacdive.dsmz.de/strain/133307"},{"substrate":"L-arginine","exchange":"EX_arg__L_e","category":"carbon","phenotype":"positive","n_strains":1,"n_positive":1,"n_negative":0,"sources":["bacdive"],"kinds":["degradation"],"citation":"BacDive strain 133307 (Reimer LC et al., BacDive 2022, NAR); https://bacdive.dsmz.de/strain/133307"},{"substrate":"L-asparagine","exchange":"EX_asn__L_e","category":"carbon","phenotype":"positive","n_strains":1,"n_positive":1,"n_negative":0,"sources":["bacdive"],"kinds":["degradation"],"citation":"BacDive strain 133307 (Reimer LC et al., BacDive 2022, NAR); https://bacdive.dsmz.de/strain/133307"},{"substrate":"L-proline","exchange":"EX_pro__L_e","category":"carbon","phenotype":"positive","n_strains":1,"n_positive":1,"n_negative":0,"sources":["bacdive"],"kinds":["degradation"],"citation":"BacDive strain 133307 (Reimer LC et al., BacDive 2022, NAR); https://bacdive.dsmz.de/strain/133307"},{"substrate":"L-tyrosine","exchange":"EX_tyr__L_e","category":"carbon","phenotype":"positive","n_strains":1,"n_positive":1,"n_negative":0,"sources":["bacdive"],"kinds":["degradation"],"citation":"BacDive strain 133307 (Reimer LC et al., BacDive 2022, NAR); https://bacdive.dsmz.de/strain/133307"},{"substrate":"lactose","exchange":null,"category":"carbon","phenotype":"positive","n_strains":2,"n_positive":2,"n_negative":0,"sources":["bacdive"],"kinds":["builds acid from","carbon source"],"citation":"BacDive strain 133307 (Reimer LC et al., BacDive 2022, NAR); https://bacdive.dsmz.de/strain/133307"},{"substrate":"maltose","exchange":null,"category":"carbon","phenotype":"positive","n_strains":2,"n_positive":2,"n_negative":0,"sources":["bacdive"],"kinds":["builds acid from","carbon source"],"citation":"BacDive strain 133307 (Reimer LC et al., BacDive 2022, NAR); https://bacdive.dsmz.de/strain/133307"},{"substrate":"mannitol","exchange":"EX_mnl_e","category":"carbon","phenotype":"positive","n_strains":2,"n_positive":2,"n_negative":0,"sources":["bacdive"],"kinds":["builds acid from","carbon source"],"citation":"BacDive strain 133307 (Reimer LC et al., BacDive 2022, NAR); https://bacdive.dsmz.de/strain/133307"},{"substrate":"mannose","exchange":"EX_man_e","category":"carbon","phenotype":"positive","n_strains":2,"n_positive":2,"n_negative":0,"sources":["bacdive"],"kinds":["builds acid from","carbon source"],"citation":"BacDive strain 133307 (Reimer LC et al., BacDive 2022, NAR); https://bacdive.dsmz.de/strain/133307"},{"substrate":"ribose","exchange":"EX_rib__D_e","category":"carbon","phenotype":"positive","n_strains":2,"n_positive":2,"n_negative":0,"sources":["bacdive"],"kinds":["builds acid from","carbon source"],"citation":"BacDive strain 133307 (Reimer LC et al., BacDive 2022, NAR); https://bacdive.dsmz.de/strain/133307"},{"substrate":"salicin","exchange":null,"category":"carbon","phenotype":"positive","n_strains":2,"n_positive":2,"n_negative":0,"sources":["bacdive"],"kinds":["builds acid from","carbon source"],"citation":"BacDive strain 133307 (Reimer LC et al., BacDive 2022, NAR); https://bacdive.dsmz.de/strain/133307"},{"substrate":"skimmed milk","exchange":null,"category":"carbon","phenotype":"positive","n_strains":1,"n_positive":1,"n_negative":0,"sources":["bacdive"],"kinds":["degradation"],"citation":"BacDive strain 133307 (Reimer LC et al., BacDive 2022, NAR); https://bacdive.dsmz.de/strain/133307"},{"substrate":"starch","exchange":null,"category":"carbon","phenotype":"positive","n_strains":1,"n_positive":1,"n_negative":0,"sources":["bacdive"],"kinds":["hydrolysis"],"citation":"BacDive strain 133307 (Reimer LC et al., BacDive 2022, NAR); https://bacdive.dsmz.de/strain/133307"},{"substrate":"sucrose","exchange":null,"category":"carbon","phenotype":"positive","n_strains":2,"n_positive":2,"n_negative":0,"sources":["bacdive"],"kinds":["builds acid from","carbon source"],"citation":"BacDive strain 133307 (Reimer LC et al., BacDive 2022, NAR); https://bacdive.dsmz.de/strain/133307"},{"substrate":"tween 60","exchange":null,"category":"carbon","phenotype":"positive","n_strains":1,"n_positive":1,"n_negative":0,"sources":["bacdive"],"kinds":["hydrolysis"],"citation":"BacDive strain 133307 (Reimer LC et al., BacDive 2022, NAR); https://bacdive.dsmz.de/strain/133307"},{"substrate":"tween 80","exchange":null,"category":"carbon","phenotype":"positive","n_strains":1,"n_positive":1,"n_negative":0,"sources":["bacdive"],"kinds":["hydrolysis"],"citation":"BacDive strain 133307 (Reimer LC et al., BacDive 2022, NAR); https://bacdive.dsmz.de/strain/133307"},{"substrate":"urea","exchange":"EX_urea_e","category":"carbon","phenotype":"positive","n_strains":1,"n_positive":1,"n_negative":0,"sources":["bacdive"],"kinds":["degradation"],"citation":"BacDive strain 133307 (Reimer LC et al., BacDive 2022, NAR); https://bacdive.dsmz.de/strain/133307"},{"substrate":"valine","exchange":"EX_val__L_e","category":"carbon","phenotype":"positive","n_strains":1,"n_positive":1,"n_negative":0,"sources":["bacdive"],"kinds":["degradation"],"citation":"BacDive strain 133307 (Reimer LC et al., BacDive 2022, NAR); https://bacdive.dsmz.de/strain/133307"},{"substrate":"xanthine","exchange":"EX_xan_e","category":"carbon","phenotype":"positive","n_strains":1,"n_positive":1,"n_negative":0,"sources":["bacdive"],"kinds":["degradation"],"citation":"BacDive strain 133307 (Reimer LC et al., BacDive 2022, NAR); https://bacdive.dsmz.de/strain/133307"},{"substrate":"xylose","exchange":"EX_xyl__D_e","category":"carbon","phenotype":"positive","n_strains":2,"n_positive":2,"n_negative":0,"sources":["bacdive"],"kinds":["builds acid from","carbon source"],"citation":"BacDive strain 133307 (Reimer LC et al., BacDive 2022, NAR); https://bacdive.dsmz.de/strain/133307"},{"substrate":"carboxymethylcellulose","exchange":null,"category":"carbon","phenotype":"variable","n_strains":1,"n_positive":0,"n_negative":0,"sources":["bacdive"],"kinds":["hydrolysis"],"citation":"BacDive strain 133307 (Reimer LC et al., BacDive 2022, NAR); https://bacdive.dsmz.de/strain/133307"},{"substrate":"cysteine","exchange":"EX_cys__L_e","category":"carbon","phenotype":"variable","n_strains":1,"n_positive":0,"n_negative":0,"sources":["bacdive"],"kinds":["degradation"],"citation":"BacDive strain 133307 (Reimer LC et al., BacDive 2022, NAR); https://bacdive.dsmz.de/strain/133307"}]}