{"species":"Lacticaseibacillus nasuensis","superkingdom":"Bacteria","n_records":0,"n_mu":0,"n_phenotypes":52,"growth_records":[],"phenotypes":[{"substrate":"2-dehydro-D-gluconate","exchange":"EX_2dhglcn_e","category":"carbon","phenotype":"positive","n_strains":1,"n_positive":1,"n_negative":0,"sources":["bacdive"],"kinds":["carbon source"],"citation":"BacDive strain 6703 (Reimer LC et al., BacDive 2022, NAR); https://bacdive.dsmz.de/strain/6703"},{"substrate":"arabinose","exchange":"EX_arab__L_e","category":"carbon","phenotype":"positive","n_strains":1,"n_positive":1,"n_negative":0,"sources":["bacdive"],"kinds":["carbon source"],"citation":"BacDive strain 6703 (Reimer LC et al., BacDive 2022, NAR); https://bacdive.dsmz.de/strain/6703"},{"substrate":"maltose","exchange":null,"category":"carbon","phenotype":"variable","n_strains":2,"n_positive":1,"n_negative":1,"sources":["bacdive"],"kinds":["builds acid from","carbon source"],"citation":"BacDive strain 6703 (Reimer LC et al., BacDive 2022, NAR); https://bacdive.dsmz.de/strain/6703"},{"substrate":"ribose","exchange":"EX_rib__D_e","category":"carbon","phenotype":"positive","n_strains":1,"n_positive":1,"n_negative":0,"sources":["bacdive"],"kinds":["carbon source"],"citation":"BacDive strain 6703 (Reimer LC et al., BacDive 2022, NAR); https://bacdive.dsmz.de/strain/6703"},{"substrate":"xylose","exchange":"EX_xyl__D_e","category":"carbon","phenotype":"positive","n_strains":1,"n_positive":1,"n_negative":0,"sources":["bacdive"],"kinds":["carbon source"],"citation":"BacDive strain 6703 (Reimer LC et al., BacDive 2022, NAR); https://bacdive.dsmz.de/strain/6703"},{"substrate":"Potassium 5-ketogluconate","exchange":null,"category":"carbon","phenotype":"negative","n_strains":1,"n_positive":0,"n_negative":1,"sources":["bacdive"],"kinds":["builds acid from"],"citation":"BacDive strain 6703 (Reimer LC et al., BacDive 2022, NAR); https://bacdive.dsmz.de/strain/6703"},{"substrate":"amygdalin","exchange":null,"category":"carbon","phenotype":"negative","n_strains":1,"n_positive":0,"n_negative":1,"sources":["bacdive"],"kinds":["builds acid from"],"citation":"BacDive strain 6703 (Reimer LC et al., BacDive 2022, NAR); https://bacdive.dsmz.de/strain/6703"},{"substrate":"methyl alpha-D-glucopyranoside","exchange":null,"category":"carbon","phenotype":"negative","n_strains":1,"n_positive":0,"n_negative":1,"sources":["bacdive"],"kinds":["builds acid from"],"citation":"BacDive strain 6703 (Reimer LC et al., BacDive 2022, NAR); https://bacdive.dsmz.de/strain/6703"},{"substrate":"Potassium 2-ketogluconate","exchange":null,"category":"carbon","phenotype":"negative","n_strains":1,"n_positive":0,"n_negative":1,"sources":["bacdive"],"kinds":["builds acid from"],"citation":"BacDive strain 6703 (Reimer LC et al., BacDive 2022, NAR); https://bacdive.dsmz.de/strain/6703"},{"substrate":"gluconate","exchange":"EX_glcn_e","category":"carbon","phenotype":"negative","n_strains":1,"n_positive":0,"n_negative":1,"sources":["bacdive"],"kinds":["builds acid from"],"citation":"BacDive strain 6703 (Reimer LC et al., BacDive 2022, NAR); https://bacdive.dsmz.de/strain/6703"},{"substrate":"L-arabitol","exchange":"EX_abt__D_e","category":"carbon","phenotype":"negative","n_strains":1,"n_positive":0,"n_negative":1,"sources":["bacdive"],"kinds":["builds acid from"],"citation":"BacDive strain 6703 (Reimer LC et al., BacDive 2022, NAR); https://bacdive.dsmz.de/strain/6703"},{"substrate":"D-arabitol","exchange":"EX_abt__D_e","category":"carbon","phenotype":"negative","n_strains":1,"n_positive":0,"n_negative":1,"sources":["bacdive"],"kinds":["builds acid from"],"citation":"BacDive strain 6703 (Reimer LC et al., BacDive 2022, NAR); https://bacdive.dsmz.de/strain/6703"},{"substrate":"L-fucose","exchange":"EX_fuc__L_e","category":"carbon","phenotype":"negative","n_strains":1,"n_positive":0,"n_negative":1,"sources":["bacdive"],"kinds":["builds acid from"],"citation":"BacDive strain 6703 (Reimer LC et al., BacDive 2022, NAR); https://bacdive.dsmz.de/strain/6703"},{"substrate":"D-fucose","exchange":"EX_fuc__L_e","category":"carbon","phenotype":"negative","n_strains":1,"n_positive":0,"n_negative":1,"sources":["bacdive"],"kinds":["builds acid from"],"citation":"BacDive strain 6703 (Reimer LC et al., BacDive 2022, NAR); https://bacdive.dsmz.de/strain/6703"},{"substrate":"D-tagatose","exchange":"EX_tag__D_e","category":"carbon","phenotype":"negative","n_strains":1,"n_positive":0,"n_negative":1,"sources":["bacdive"],"kinds":["builds acid from"],"citation":"BacDive strain 6703 (Reimer LC et al., BacDive 2022, NAR); https://bacdive.dsmz.de/strain/6703"},{"substrate":"D-lyxose","exchange":"EX_lyx__L_e","category":"carbon","phenotype":"negative","n_strains":1,"n_positive":0,"n_negative":1,"sources":["bacdive"],"kinds":["builds acid from"],"citation":"BacDive strain 6703 (Reimer LC et al., BacDive 2022, NAR); https://bacdive.dsmz.de/strain/6703"},{"substrate":"turanose","exchange":null,"category":"carbon","phenotype":"negative","n_strains":1,"n_positive":0,"n_negative":1,"sources":["bacdive"],"kinds":["builds acid from"],"citation":"BacDive strain 6703 (Reimer LC et al., BacDive 2022, NAR); https://bacdive.dsmz.de/strain/6703"},{"substrate":"gentiobiose","exchange":null,"category":"carbon","phenotype":"negative","n_strains":1,"n_positive":0,"n_negative":1,"sources":["bacdive"],"kinds":["builds acid from"],"citation":"BacDive strain 6703 (Reimer LC et al., BacDive 2022, NAR); https://bacdive.dsmz.de/strain/6703"},{"substrate":"xylitol","exchange":null,"category":"carbon","phenotype":"negative","n_strains":1,"n_positive":0,"n_negative":1,"sources":["bacdive"],"kinds":["builds acid from"],"citation":"BacDive strain 6703 (Reimer LC et al., BacDive 2022, NAR); https://bacdive.dsmz.de/strain/6703"},{"substrate":"glycogen","exchange":null,"category":"carbon","phenotype":"negative","n_strains":1,"n_positive":0,"n_negative":1,"sources":["bacdive"],"kinds":["builds acid from"],"citation":"BacDive strain 6703 (Reimer LC et al., BacDive 2022, NAR); https://bacdive.dsmz.de/strain/6703"},{"substrate":"starch","exchange":null,"category":"carbon","phenotype":"negative","n_strains":1,"n_positive":0,"n_negative":1,"sources":["bacdive"],"kinds":["builds acid from"],"citation":"BacDive strain 6703 (Reimer LC et al., BacDive 2022, NAR); https://bacdive.dsmz.de/strain/6703"},{"substrate":"raffinose","exchange":null,"category":"carbon","phenotype":"negative","n_strains":1,"n_positive":0,"n_negative":1,"sources":["bacdive"],"kinds":["builds acid from"],"citation":"BacDive strain 6703 (Reimer LC et al., BacDive 2022, NAR); https://bacdive.dsmz.de/strain/6703"},{"substrate":"melezitose","exchange":null,"category":"carbon","phenotype":"negative","n_strains":1,"n_positive":0,"n_negative":1,"sources":["bacdive"],"kinds":["builds acid from"],"citation":"BacDive strain 6703 (Reimer LC et al., BacDive 2022, NAR); https://bacdive.dsmz.de/strain/6703"},{"substrate":"inulin","exchange":null,"category":"carbon","phenotype":"negative","n_strains":1,"n_positive":0,"n_negative":1,"sources":["bacdive"],"kinds":["builds acid from"],"citation":"BacDive strain 6703 (Reimer LC et al., BacDive 2022, NAR); https://bacdive.dsmz.de/strain/6703"},{"substrate":"trehalose","exchange":"EX_tre_e","category":"carbon","phenotype":"negative","n_strains":1,"n_positive":0,"n_negative":1,"sources":["bacdive"],"kinds":["builds acid from"],"citation":"BacDive strain 6703 (Reimer LC et al., BacDive 2022, NAR); https://bacdive.dsmz.de/strain/6703"},{"substrate":"sucrose","exchange":null,"category":"carbon","phenotype":"negative","n_strains":1,"n_positive":0,"n_negative":1,"sources":["bacdive"],"kinds":["builds acid from"],"citation":"BacDive strain 6703 (Reimer LC et al., BacDive 2022, NAR); https://bacdive.dsmz.de/strain/6703"},{"substrate":"melibiose","exchange":null,"category":"carbon","phenotype":"negative","n_strains":1,"n_positive":0,"n_negative":1,"sources":["bacdive"],"kinds":["builds acid from"],"citation":"BacDive strain 6703 (Reimer LC et al., BacDive 2022, NAR); https://bacdive.dsmz.de/strain/6703"},{"substrate":"lactose","exchange":null,"category":"carbon","phenotype":"negative","n_strains":1,"n_positive":0,"n_negative":1,"sources":["bacdive"],"kinds":["builds acid from"],"citation":"BacDive strain 6703 (Reimer LC et al., BacDive 2022, NAR); https://bacdive.dsmz.de/strain/6703"},{"substrate":"cellobiose","exchange":"EX_cellb_e","category":"carbon","phenotype":"negative","n_strains":1,"n_positive":0,"n_negative":1,"sources":["bacdive"],"kinds":["builds acid from"],"citation":"BacDive strain 6703 (Reimer LC et al., BacDive 2022, NAR); https://bacdive.dsmz.de/strain/6703"},{"substrate":"salicin","exchange":null,"category":"carbon","phenotype":"negative","n_strains":1,"n_positive":0,"n_negative":1,"sources":["bacdive"],"kinds":["builds acid from"],"citation":"BacDive strain 6703 (Reimer LC et al., BacDive 2022, NAR); https://bacdive.dsmz.de/strain/6703"},{"substrate":"arbutin","exchange":null,"category":"carbon","phenotype":"negative","n_strains":1,"n_positive":0,"n_negative":1,"sources":["bacdive"],"kinds":["builds acid from"],"citation":"BacDive strain 6703 (Reimer LC et al., BacDive 2022, NAR); https://bacdive.dsmz.de/strain/6703"},{"substrate":"N-acetylglucosamine","exchange":null,"category":"carbon","phenotype":"positive","n_strains":1,"n_positive":1,"n_negative":0,"sources":["bacdive"],"kinds":["builds acid from"],"citation":"BacDive strain 6703 (Reimer LC et al., BacDive 2022, NAR); https://bacdive.dsmz.de/strain/6703"},{"substrate":"methyl alpha-D-mannoside","exchange":null,"category":"carbon","phenotype":"negative","n_strains":1,"n_positive":0,"n_negative":1,"sources":["bacdive"],"kinds":["builds acid from"],"citation":"BacDive strain 6703 (Reimer LC et al., BacDive 2022, NAR); https://bacdive.dsmz.de/strain/6703"},{"substrate":"D-sorbitol","exchange":"EX_sbt__D_e","category":"carbon","phenotype":"negative","n_strains":1,"n_positive":0,"n_negative":1,"sources":["bacdive"],"kinds":["builds acid from"],"citation":"BacDive strain 6703 (Reimer LC et al., BacDive 2022, NAR); https://bacdive.dsmz.de/strain/6703"},{"substrate":"D-mannitol","exchange":"EX_mnl_e","category":"carbon","phenotype":"negative","n_strains":1,"n_positive":0,"n_negative":1,"sources":["bacdive"],"kinds":["builds acid from"],"citation":"BacDive strain 6703 (Reimer LC et al., BacDive 2022, NAR); https://bacdive.dsmz.de/strain/6703"},{"substrate":"myo-inositol","exchange":"EX_inost_e","category":"carbon","phenotype":"negative","n_strains":1,"n_positive":0,"n_negative":1,"sources":["bacdive"],"kinds":["builds acid from"],"citation":"BacDive strain 6703 (Reimer LC et al., BacDive 2022, NAR); https://bacdive.dsmz.de/strain/6703"},{"substrate":"galactitol","exchange":"EX_galt_e","category":"carbon","phenotype":"negative","n_strains":1,"n_positive":0,"n_negative":1,"sources":["bacdive"],"kinds":["builds acid from"],"citation":"BacDive strain 6703 (Reimer LC et al., BacDive 2022, NAR); https://bacdive.dsmz.de/strain/6703"},{"substrate":"L-rhamnose","exchange":"EX_rmn_e","category":"carbon","phenotype":"negative","n_strains":1,"n_positive":0,"n_negative":1,"sources":["bacdive"],"kinds":["builds acid from"],"citation":"BacDive strain 6703 (Reimer LC et al., BacDive 2022, NAR); https://bacdive.dsmz.de/strain/6703"},{"substrate":"L-sorbose","exchange":null,"category":"carbon","phenotype":"negative","n_strains":1,"n_positive":0,"n_negative":1,"sources":["bacdive"],"kinds":["builds acid from"],"citation":"BacDive strain 6703 (Reimer LC et al., BacDive 2022, NAR); https://bacdive.dsmz.de/strain/6703"},{"substrate":"D-mannose","exchange":"EX_man_e","category":"carbon","phenotype":"positive","n_strains":1,"n_positive":1,"n_negative":0,"sources":["bacdive"],"kinds":["builds acid from"],"citation":"BacDive strain 6703 (Reimer LC et al., BacDive 2022, NAR); https://bacdive.dsmz.de/strain/6703"},{"substrate":"D-fructose","exchange":"EX_fru_e","category":"carbon","phenotype":"positive","n_strains":1,"n_positive":1,"n_negative":0,"sources":["bacdive"],"kinds":["builds acid from"],"citation":"BacDive strain 6703 (Reimer LC et al., BacDive 2022, NAR); https://bacdive.dsmz.de/strain/6703"},{"substrate":"D-glucose","exchange":"EX_glc__D_e","category":"carbon","phenotype":"positive","n_strains":1,"n_positive":1,"n_negative":0,"sources":["bacdive"],"kinds":["builds acid from"],"citation":"BacDive strain 6703 (Reimer LC et al., BacDive 2022, NAR); https://bacdive.dsmz.de/strain/6703"},{"substrate":"D-galactose","exchange":"EX_gal_e","category":"carbon","phenotype":"negative","n_strains":1,"n_positive":0,"n_negative":1,"sources":["bacdive"],"kinds":["builds acid from"],"citation":"BacDive strain 6703 (Reimer LC et al., BacDive 2022, NAR); https://bacdive.dsmz.de/strain/6703"},{"substrate":"methyl beta-D-xylopyranoside","exchange":null,"category":"carbon","phenotype":"negative","n_strains":1,"n_positive":0,"n_negative":1,"sources":["bacdive"],"kinds":["builds acid from"],"citation":"BacDive strain 6703 (Reimer LC et al., BacDive 2022, NAR); https://bacdive.dsmz.de/strain/6703"},{"substrate":"ribitol","exchange":"EX_rbt_e","category":"carbon","phenotype":"negative","n_strains":1,"n_positive":0,"n_negative":1,"sources":["bacdive"],"kinds":["builds acid from"],"citation":"BacDive strain 6703 (Reimer LC et al., BacDive 2022, NAR); https://bacdive.dsmz.de/strain/6703"},{"substrate":"L-xylose","exchange":"EX_xyl__D_e","category":"carbon","phenotype":"negative","n_strains":1,"n_positive":0,"n_negative":1,"sources":["bacdive"],"kinds":["builds acid from"],"citation":"BacDive strain 6703 (Reimer LC et al., BacDive 2022, NAR); https://bacdive.dsmz.de/strain/6703"},{"substrate":"D-xylose","exchange":"EX_xyl__D_e","category":"carbon","phenotype":"negative","n_strains":1,"n_positive":0,"n_negative":1,"sources":["bacdive"],"kinds":["builds acid from"],"citation":"BacDive strain 6703 (Reimer LC et al., BacDive 2022, NAR); https://bacdive.dsmz.de/strain/6703"},{"substrate":"D-ribose","exchange":"EX_rib__D_e","category":"carbon","phenotype":"positive","n_strains":1,"n_positive":1,"n_negative":0,"sources":["bacdive"],"kinds":["builds acid from"],"citation":"BacDive strain 6703 (Reimer LC et al., BacDive 2022, NAR); https://bacdive.dsmz.de/strain/6703"},{"substrate":"L-arabinose","exchange":"EX_arab__L_e","category":"carbon","phenotype":"negative","n_strains":1,"n_positive":0,"n_negative":1,"sources":["bacdive"],"kinds":["builds acid from"],"citation":"BacDive strain 6703 (Reimer LC et al., BacDive 2022, NAR); https://bacdive.dsmz.de/strain/6703"},{"substrate":"D-arabinose","exchange":"EX_arab__L_e","category":"carbon","phenotype":"negative","n_strains":1,"n_positive":0,"n_negative":1,"sources":["bacdive"],"kinds":["builds acid from"],"citation":"BacDive strain 6703 (Reimer LC et al., BacDive 2022, NAR); https://bacdive.dsmz.de/strain/6703"},{"substrate":"erythritol","exchange":null,"category":"carbon","phenotype":"negative","n_strains":1,"n_positive":0,"n_negative":1,"sources":["bacdive"],"kinds":["builds acid from"],"citation":"BacDive strain 6703 (Reimer LC et al., BacDive 2022, NAR); https://bacdive.dsmz.de/strain/6703"},{"substrate":"glycerol","exchange":"EX_glyc_e","category":"carbon","phenotype":"negative","n_strains":1,"n_positive":0,"n_negative":1,"sources":["bacdive"],"kinds":["builds acid from"],"citation":"BacDive strain 6703 (Reimer LC et al., BacDive 2022, NAR); https://bacdive.dsmz.de/strain/6703"}]}