{"species":"Macrococcus sp","superkingdom":"","n_records":0,"n_mu":0,"n_phenotypes":25,"growth_records":[],"phenotypes":[{"substrate":"urea","exchange":"EX_urea_e","category":"carbon","phenotype":"negative","n_strains":3,"n_positive":1,"n_negative":2,"sources":["bacdive"],"kinds":["hydrolysis"],"citation":"BacDive strain 148960 (Reimer LC et al., BacDive 2022, NAR); https://bacdive.dsmz.de/strain/148960"},{"substrate":"arginine","exchange":"EX_arg__L_e","category":"carbon","phenotype":"variable","n_strains":2,"n_positive":1,"n_negative":1,"sources":["bacdive"],"kinds":["hydrolysis"],"citation":"BacDive strain 148960 (Reimer LC et al., BacDive 2022, NAR); https://bacdive.dsmz.de/strain/148960"},{"substrate":"N-acetylglucosamine","exchange":null,"category":"carbon","phenotype":"negative","n_strains":2,"n_positive":0,"n_negative":2,"sources":["bacdive"],"kinds":["builds acid from","fermentation"],"citation":"BacDive strain 148960 (Reimer LC et al., BacDive 2022, NAR); https://bacdive.dsmz.de/strain/148960"},{"substrate":"methyl alpha-D-glucopyranoside","exchange":null,"category":"carbon","phenotype":"positive","n_strains":1,"n_positive":1,"n_negative":0,"sources":["bacdive"],"kinds":["builds acid from"],"citation":"BacDive strain 148960 (Reimer LC et al., BacDive 2022, NAR); https://bacdive.dsmz.de/strain/148960"},{"substrate":"sucrose","exchange":null,"category":"carbon","phenotype":"positive","n_strains":3,"n_positive":2,"n_negative":1,"sources":["bacdive"],"kinds":["builds acid from","fermentation"],"citation":"BacDive strain 148960 (Reimer LC et al., BacDive 2022, NAR); https://bacdive.dsmz.de/strain/148960"},{"substrate":"D-xylose","exchange":"EX_xyl__D_e","category":"carbon","phenotype":"negative","n_strains":2,"n_positive":0,"n_negative":2,"sources":["bacdive"],"kinds":["builds acid from","fermentation"],"citation":"BacDive strain 148960 (Reimer LC et al., BacDive 2022, NAR); https://bacdive.dsmz.de/strain/148960"},{"substrate":"raffinose","exchange":null,"category":"carbon","phenotype":"variable","n_strains":2,"n_positive":1,"n_negative":1,"sources":["bacdive"],"kinds":["builds acid from","fermentation"],"citation":"BacDive strain 148960 (Reimer LC et al., BacDive 2022, NAR); https://bacdive.dsmz.de/strain/148960"},{"substrate":"nitrate","exchange":"EX_no3_e","category":"carbon","phenotype":"positive","n_strains":3,"n_positive":2,"n_negative":1,"sources":["bacdive"],"kinds":["reduction"],"citation":"BacDive strain 148960 (Reimer LC et al., BacDive 2022, NAR); https://bacdive.dsmz.de/strain/148960"},{"substrate":"melibiose","exchange":null,"category":"carbon","phenotype":"negative","n_strains":1,"n_positive":0,"n_negative":1,"sources":["bacdive"],"kinds":["builds acid from"],"citation":"BacDive strain 148960 (Reimer LC et al., BacDive 2022, NAR); https://bacdive.dsmz.de/strain/148960"},{"substrate":"xylitol","exchange":null,"category":"carbon","phenotype":"negative","n_strains":1,"n_positive":0,"n_negative":1,"sources":["bacdive"],"kinds":["builds acid from"],"citation":"BacDive strain 148960 (Reimer LC et al., BacDive 2022, NAR); https://bacdive.dsmz.de/strain/148960"},{"substrate":"D-mannitol","exchange":"EX_mnl_e","category":"carbon","phenotype":"negative","n_strains":3,"n_positive":1,"n_negative":2,"sources":["bacdive"],"kinds":["builds acid from","fermentation"],"citation":"BacDive strain 148960 (Reimer LC et al., BacDive 2022, NAR); https://bacdive.dsmz.de/strain/148960"},{"substrate":"trehalose","exchange":"EX_tre_e","category":"carbon","phenotype":"negative","n_strains":2,"n_positive":0,"n_negative":2,"sources":["bacdive"],"kinds":["builds acid from","fermentation"],"citation":"BacDive strain 148960 (Reimer LC et al., BacDive 2022, NAR); https://bacdive.dsmz.de/strain/148960"},{"substrate":"maltose","exchange":null,"category":"carbon","phenotype":"positive","n_strains":3,"n_positive":3,"n_negative":0,"sources":["bacdive"],"kinds":["builds acid from","fermentation"],"citation":"BacDive strain 148960 (Reimer LC et al., BacDive 2022, NAR); https://bacdive.dsmz.de/strain/148960"},{"substrate":"lactose","exchange":null,"category":"carbon","phenotype":"negative","n_strains":3,"n_positive":1,"n_negative":2,"sources":["bacdive"],"kinds":["builds acid from","fermentation"],"citation":"BacDive strain 148960 (Reimer LC et al., BacDive 2022, NAR); https://bacdive.dsmz.de/strain/148960"},{"substrate":"D-fructose","exchange":"EX_fru_e","category":"carbon","phenotype":"positive","n_strains":2,"n_positive":2,"n_negative":0,"sources":["bacdive"],"kinds":["builds acid from","fermentation"],"citation":"BacDive strain 148960 (Reimer LC et al., BacDive 2022, NAR); https://bacdive.dsmz.de/strain/148960"},{"substrate":"D-mannose","exchange":"EX_man_e","category":"carbon","phenotype":"variable","n_strains":2,"n_positive":1,"n_negative":1,"sources":["bacdive"],"kinds":["builds acid from","fermentation"],"citation":"BacDive strain 148960 (Reimer LC et al., BacDive 2022, NAR); https://bacdive.dsmz.de/strain/148960"},{"substrate":"D-glucose","exchange":"EX_glc__D_e","category":"carbon","phenotype":"positive","n_strains":3,"n_positive":2,"n_negative":1,"sources":["bacdive"],"kinds":["builds acid from","fermentation"],"citation":"BacDive strain 148960 (Reimer LC et al., BacDive 2022, NAR); https://bacdive.dsmz.de/strain/148960"},{"substrate":"arabinose","exchange":"EX_arab__L_e","category":"carbon","phenotype":"negative","n_strains":1,"n_positive":0,"n_negative":1,"sources":["bacdive"],"kinds":["fermentation"],"citation":"BacDive strain 148960 (Reimer LC et al., BacDive 2022, NAR); https://bacdive.dsmz.de/strain/148960"},{"substrate":"cellobiose","exchange":"EX_cellb_e","category":"carbon","phenotype":"negative","n_strains":1,"n_positive":0,"n_negative":1,"sources":["bacdive"],"kinds":["fermentation"],"citation":"BacDive strain 148960 (Reimer LC et al., BacDive 2022, NAR); https://bacdive.dsmz.de/strain/148960"},{"substrate":"D-ribose","exchange":"EX_rib__D_e","category":"carbon","phenotype":"variable","n_strains":2,"n_positive":1,"n_negative":1,"sources":["bacdive"],"kinds":["fermentation"],"citation":"BacDive strain 148960 (Reimer LC et al., BacDive 2022, NAR); https://bacdive.dsmz.de/strain/148960"},{"substrate":"esculin","exchange":"EX_escul_e","category":"carbon","phenotype":"variable","n_strains":2,"n_positive":1,"n_negative":1,"sources":["bacdive"],"kinds":["hydrolysis"],"citation":"BacDive strain 148960 (Reimer LC et al., BacDive 2022, NAR); https://bacdive.dsmz.de/strain/148960"},{"substrate":"ornithine","exchange":"EX_orn__D_e","category":"carbon","phenotype":"negative","n_strains":1,"n_positive":0,"n_negative":1,"sources":["bacdive"],"kinds":["degradation"],"citation":"BacDive strain 148960 (Reimer LC et al., BacDive 2022, NAR); https://bacdive.dsmz.de/strain/148960"},{"substrate":"glycogen","exchange":null,"category":"carbon","phenotype":"negative","n_strains":1,"n_positive":0,"n_negative":1,"sources":["bacdive"],"kinds":["fermentation"],"citation":"BacDive strain 148960 (Reimer LC et al., BacDive 2022, NAR); https://bacdive.dsmz.de/strain/148960"},{"substrate":"gelatin","exchange":null,"category":"carbon","phenotype":"positive","n_strains":1,"n_positive":1,"n_negative":0,"sources":["bacdive"],"kinds":["hydrolysis"],"citation":"BacDive strain 148960 (Reimer LC et al., BacDive 2022, NAR); https://bacdive.dsmz.de/strain/148960"},{"substrate":"turanose","exchange":null,"category":"carbon","phenotype":"negative","n_strains":1,"n_positive":0,"n_negative":1,"sources":["bacdive"],"kinds":["fermentation"],"citation":"BacDive strain 148960 (Reimer LC et al., BacDive 2022, NAR); https://bacdive.dsmz.de/strain/148960"}]}