{"species":"Maribacter pelagius","superkingdom":"","n_records":0,"n_mu":0,"n_phenotypes":55,"growth_records":[],"phenotypes":[{"substrate":"amygdalin","exchange":null,"category":"carbon","phenotype":"negative","n_strains":1,"n_positive":0,"n_negative":1,"sources":["bacdive"],"kinds":["builds acid from"],"citation":"BacDive strain 140774 (Reimer LC et al., BacDive 2022, NAR); https://bacdive.dsmz.de/strain/140774"},{"substrate":"arabinose","exchange":"EX_arab__L_e","category":"carbon","phenotype":"negative","n_strains":1,"n_positive":0,"n_negative":1,"sources":["bacdive"],"kinds":["builds acid from"],"citation":"BacDive strain 140774 (Reimer LC et al., BacDive 2022, NAR); https://bacdive.dsmz.de/strain/140774"},{"substrate":"arabinitol","exchange":null,"category":"carbon","phenotype":"negative","n_strains":1,"n_positive":0,"n_negative":1,"sources":["bacdive"],"kinds":["builds acid from"],"citation":"BacDive strain 140774 (Reimer LC et al., BacDive 2022, NAR); https://bacdive.dsmz.de/strain/140774"},{"substrate":"cellobiose","exchange":"EX_cellb_e","category":"carbon","phenotype":"negative","n_strains":1,"n_positive":0,"n_negative":1,"sources":["bacdive"],"kinds":["builds acid from"],"citation":"BacDive strain 140774 (Reimer LC et al., BacDive 2022, NAR); https://bacdive.dsmz.de/strain/140774"},{"substrate":"ribitol","exchange":"EX_rbt_e","category":"carbon","phenotype":"negative","n_strains":1,"n_positive":0,"n_negative":1,"sources":["bacdive"],"kinds":["builds acid from"],"citation":"BacDive strain 140774 (Reimer LC et al., BacDive 2022, NAR); https://bacdive.dsmz.de/strain/140774"},{"substrate":"D-fructose","exchange":"EX_fru_e","category":"carbon","phenotype":"negative","n_strains":1,"n_positive":0,"n_negative":1,"sources":["bacdive"],"kinds":["builds acid from"],"citation":"BacDive strain 140774 (Reimer LC et al., BacDive 2022, NAR); https://bacdive.dsmz.de/strain/140774"},{"substrate":"D-galactose","exchange":"EX_gal_e","category":"carbon","phenotype":"negative","n_strains":1,"n_positive":0,"n_negative":1,"sources":["bacdive"],"kinds":["builds acid from"],"citation":"BacDive strain 140774 (Reimer LC et al., BacDive 2022, NAR); https://bacdive.dsmz.de/strain/140774"},{"substrate":"D-glucose","exchange":"EX_glc__D_e","category":"carbon","phenotype":"negative","n_strains":2,"n_positive":0,"n_negative":2,"sources":["bacdive"],"kinds":["builds acid from","carbon source"],"citation":"BacDive strain 140774 (Reimer LC et al., BacDive 2022, NAR); https://bacdive.dsmz.de/strain/140774"},{"substrate":"D-lyxose","exchange":"EX_lyx__L_e","category":"carbon","phenotype":"negative","n_strains":1,"n_positive":0,"n_negative":1,"sources":["bacdive"],"kinds":["builds acid from"],"citation":"BacDive strain 140774 (Reimer LC et al., BacDive 2022, NAR); https://bacdive.dsmz.de/strain/140774"},{"substrate":"D-mannitol","exchange":"EX_mnl_e","category":"carbon","phenotype":"negative","n_strains":2,"n_positive":0,"n_negative":2,"sources":["bacdive"],"kinds":["builds acid from","carbon source"],"citation":"BacDive strain 140774 (Reimer LC et al., BacDive 2022, NAR); https://bacdive.dsmz.de/strain/140774"},{"substrate":"D-mannose","exchange":"EX_man_e","category":"carbon","phenotype":"negative","n_strains":2,"n_positive":0,"n_negative":2,"sources":["bacdive"],"kinds":["builds acid from","carbon source"],"citation":"BacDive strain 140774 (Reimer LC et al., BacDive 2022, NAR); https://bacdive.dsmz.de/strain/140774"},{"substrate":"D-ribose","exchange":"EX_rib__D_e","category":"carbon","phenotype":"negative","n_strains":1,"n_positive":0,"n_negative":1,"sources":["bacdive"],"kinds":["builds acid from"],"citation":"BacDive strain 140774 (Reimer LC et al., BacDive 2022, NAR); https://bacdive.dsmz.de/strain/140774"},{"substrate":"D-sorbitol","exchange":"EX_sbt__D_e","category":"carbon","phenotype":"negative","n_strains":1,"n_positive":0,"n_negative":1,"sources":["bacdive"],"kinds":["builds acid from"],"citation":"BacDive strain 140774 (Reimer LC et al., BacDive 2022, NAR); https://bacdive.dsmz.de/strain/140774"},{"substrate":"D-tagatose","exchange":"EX_tag__D_e","category":"carbon","phenotype":"negative","n_strains":1,"n_positive":0,"n_negative":1,"sources":["bacdive"],"kinds":["builds acid from"],"citation":"BacDive strain 140774 (Reimer LC et al., BacDive 2022, NAR); https://bacdive.dsmz.de/strain/140774"},{"substrate":"galactitol","exchange":"EX_galt_e","category":"carbon","phenotype":"negative","n_strains":1,"n_positive":0,"n_negative":1,"sources":["bacdive"],"kinds":["builds acid from"],"citation":"BacDive strain 140774 (Reimer LC et al., BacDive 2022, NAR); https://bacdive.dsmz.de/strain/140774"},{"substrate":"erythritol","exchange":null,"category":"carbon","phenotype":"negative","n_strains":1,"n_positive":0,"n_negative":1,"sources":["bacdive"],"kinds":["builds acid from"],"citation":"BacDive strain 140774 (Reimer LC et al., BacDive 2022, NAR); https://bacdive.dsmz.de/strain/140774"},{"substrate":"fucose","exchange":"EX_fuc__L_e","category":"carbon","phenotype":"negative","n_strains":1,"n_positive":0,"n_negative":1,"sources":["bacdive"],"kinds":["builds acid from"],"citation":"BacDive strain 140774 (Reimer LC et al., BacDive 2022, NAR); https://bacdive.dsmz.de/strain/140774"},{"substrate":"gentiobiose","exchange":null,"category":"carbon","phenotype":"negative","n_strains":1,"n_positive":0,"n_negative":1,"sources":["bacdive"],"kinds":["builds acid from"],"citation":"BacDive strain 140774 (Reimer LC et al., BacDive 2022, NAR); https://bacdive.dsmz.de/strain/140774"},{"substrate":"gluconate","exchange":"EX_glcn_e","category":"carbon","phenotype":"negative","n_strains":1,"n_positive":0,"n_negative":1,"sources":["bacdive"],"kinds":["builds acid from"],"citation":"BacDive strain 140774 (Reimer LC et al., BacDive 2022, NAR); https://bacdive.dsmz.de/strain/140774"},{"substrate":"glycerol","exchange":"EX_glyc_e","category":"carbon","phenotype":"negative","n_strains":1,"n_positive":0,"n_negative":1,"sources":["bacdive"],"kinds":["builds acid from"],"citation":"BacDive strain 140774 (Reimer LC et al., BacDive 2022, NAR); https://bacdive.dsmz.de/strain/140774"},{"substrate":"glycogen","exchange":null,"category":"carbon","phenotype":"negative","n_strains":1,"n_positive":0,"n_negative":1,"sources":["bacdive"],"kinds":["builds acid from"],"citation":"BacDive strain 140774 (Reimer LC et al., BacDive 2022, NAR); https://bacdive.dsmz.de/strain/140774"},{"substrate":"myo-inositol","exchange":"EX_inost_e","category":"carbon","phenotype":"negative","n_strains":1,"n_positive":0,"n_negative":1,"sources":["bacdive"],"kinds":["builds acid from"],"citation":"BacDive strain 140774 (Reimer LC et al., BacDive 2022, NAR); https://bacdive.dsmz.de/strain/140774"},{"substrate":"inulin","exchange":null,"category":"carbon","phenotype":"negative","n_strains":1,"n_positive":0,"n_negative":1,"sources":["bacdive"],"kinds":["builds acid from"],"citation":"BacDive strain 140774 (Reimer LC et al., BacDive 2022, NAR); https://bacdive.dsmz.de/strain/140774"},{"substrate":"L-rhamnose","exchange":"EX_rmn_e","category":"carbon","phenotype":"negative","n_strains":1,"n_positive":0,"n_negative":1,"sources":["bacdive"],"kinds":["builds acid from"],"citation":"BacDive strain 140774 (Reimer LC et al., BacDive 2022, NAR); https://bacdive.dsmz.de/strain/140774"},{"substrate":"L-sorbose","exchange":null,"category":"carbon","phenotype":"negative","n_strains":1,"n_positive":0,"n_negative":1,"sources":["bacdive"],"kinds":["builds acid from"],"citation":"BacDive strain 140774 (Reimer LC et al., BacDive 2022, NAR); https://bacdive.dsmz.de/strain/140774"},{"substrate":"lactose","exchange":null,"category":"carbon","phenotype":"negative","n_strains":1,"n_positive":0,"n_negative":1,"sources":["bacdive"],"kinds":["builds acid from"],"citation":"BacDive strain 140774 (Reimer LC et al., BacDive 2022, NAR); https://bacdive.dsmz.de/strain/140774"},{"substrate":"maltose","exchange":null,"category":"carbon","phenotype":"negative","n_strains":2,"n_positive":0,"n_negative":2,"sources":["bacdive"],"kinds":["builds acid from","carbon source"],"citation":"BacDive strain 140774 (Reimer LC et al., BacDive 2022, NAR); https://bacdive.dsmz.de/strain/140774"},{"substrate":"melezitose","exchange":null,"category":"carbon","phenotype":"negative","n_strains":1,"n_positive":0,"n_negative":1,"sources":["bacdive"],"kinds":["builds acid from"],"citation":"BacDive strain 140774 (Reimer LC et al., BacDive 2022, NAR); https://bacdive.dsmz.de/strain/140774"},{"substrate":"melibiose","exchange":null,"category":"carbon","phenotype":"negative","n_strains":1,"n_positive":0,"n_negative":1,"sources":["bacdive"],"kinds":["builds acid from"],"citation":"BacDive strain 140774 (Reimer LC et al., BacDive 2022, NAR); https://bacdive.dsmz.de/strain/140774"},{"substrate":"methyl alpha-D-mannoside","exchange":null,"category":"carbon","phenotype":"negative","n_strains":1,"n_positive":0,"n_negative":1,"sources":["bacdive"],"kinds":["builds acid from"],"citation":"BacDive strain 140774 (Reimer LC et al., BacDive 2022, NAR); https://bacdive.dsmz.de/strain/140774"},{"substrate":"methyl beta-D-xylopyranoside","exchange":null,"category":"carbon","phenotype":"negative","n_strains":1,"n_positive":0,"n_negative":1,"sources":["bacdive"],"kinds":["builds acid from"],"citation":"BacDive strain 140774 (Reimer LC et al., BacDive 2022, NAR); https://bacdive.dsmz.de/strain/140774"},{"substrate":"methyl D-glucoside","exchange":null,"category":"carbon","phenotype":"negative","n_strains":1,"n_positive":0,"n_negative":1,"sources":["bacdive"],"kinds":["builds acid from"],"citation":"BacDive strain 140774 (Reimer LC et al., BacDive 2022, NAR); https://bacdive.dsmz.de/strain/140774"},{"substrate":"N-acetylglucosamine","exchange":null,"category":"carbon","phenotype":"negative","n_strains":2,"n_positive":0,"n_negative":2,"sources":["bacdive"],"kinds":["builds acid from","carbon source"],"citation":"BacDive strain 140774 (Reimer LC et al., BacDive 2022, NAR); https://bacdive.dsmz.de/strain/140774"},{"substrate":"potassium 2-dehydro-D-gluconate","exchange":null,"category":"carbon","phenotype":"negative","n_strains":1,"n_positive":0,"n_negative":1,"sources":["bacdive"],"kinds":["builds acid from"],"citation":"BacDive strain 140774 (Reimer LC et al., BacDive 2022, NAR); https://bacdive.dsmz.de/strain/140774"},{"substrate":"potassium 5-dehydro-D-gluconate","exchange":null,"category":"carbon","phenotype":"negative","n_strains":1,"n_positive":0,"n_negative":1,"sources":["bacdive"],"kinds":["builds acid from"],"citation":"BacDive strain 140774 (Reimer LC et al., BacDive 2022, NAR); https://bacdive.dsmz.de/strain/140774"},{"substrate":"raffinose","exchange":null,"category":"carbon","phenotype":"negative","n_strains":1,"n_positive":0,"n_negative":1,"sources":["bacdive"],"kinds":["builds acid from"],"citation":"BacDive strain 140774 (Reimer LC et al., BacDive 2022, NAR); https://bacdive.dsmz.de/strain/140774"},{"substrate":"salicin","exchange":null,"category":"carbon","phenotype":"negative","n_strains":1,"n_positive":0,"n_negative":1,"sources":["bacdive"],"kinds":["builds acid from"],"citation":"BacDive strain 140774 (Reimer LC et al., BacDive 2022, NAR); https://bacdive.dsmz.de/strain/140774"},{"substrate":"starch","exchange":null,"category":"carbon","phenotype":"negative","n_strains":2,"n_positive":0,"n_negative":2,"sources":["bacdive"],"kinds":["builds acid from","hydrolysis"],"citation":"BacDive strain 140774 (Reimer LC et al., BacDive 2022, NAR); https://bacdive.dsmz.de/strain/140774"},{"substrate":"sucrose","exchange":null,"category":"carbon","phenotype":"negative","n_strains":1,"n_positive":0,"n_negative":1,"sources":["bacdive"],"kinds":["builds acid from"],"citation":"BacDive strain 140774 (Reimer LC et al., BacDive 2022, NAR); https://bacdive.dsmz.de/strain/140774"},{"substrate":"trehalose","exchange":"EX_tre_e","category":"carbon","phenotype":"negative","n_strains":1,"n_positive":0,"n_negative":1,"sources":["bacdive"],"kinds":["builds acid from"],"citation":"BacDive strain 140774 (Reimer LC et al., BacDive 2022, NAR); https://bacdive.dsmz.de/strain/140774"},{"substrate":"turanose","exchange":null,"category":"carbon","phenotype":"negative","n_strains":1,"n_positive":0,"n_negative":1,"sources":["bacdive"],"kinds":["builds acid from"],"citation":"BacDive strain 140774 (Reimer LC et al., BacDive 2022, NAR); https://bacdive.dsmz.de/strain/140774"},{"substrate":"xylitol","exchange":null,"category":"carbon","phenotype":"negative","n_strains":1,"n_positive":0,"n_negative":1,"sources":["bacdive"],"kinds":["builds acid from"],"citation":"BacDive strain 140774 (Reimer LC et al., BacDive 2022, NAR); https://bacdive.dsmz.de/strain/140774"},{"substrate":"xylose","exchange":"EX_xyl__D_e","category":"carbon","phenotype":"negative","n_strains":1,"n_positive":0,"n_negative":1,"sources":["bacdive"],"kinds":["builds acid from"],"citation":"BacDive strain 140774 (Reimer LC et al., BacDive 2022, NAR); https://bacdive.dsmz.de/strain/140774"},{"substrate":"adipate","exchange":null,"category":"carbon","phenotype":"negative","n_strains":1,"n_positive":0,"n_negative":1,"sources":["bacdive"],"kinds":["carbon source"],"citation":"BacDive strain 140774 (Reimer LC et al., BacDive 2022, NAR); https://bacdive.dsmz.de/strain/140774"},{"substrate":"L-arabinose","exchange":"EX_arab__L_e","category":"carbon","phenotype":"negative","n_strains":1,"n_positive":0,"n_negative":1,"sources":["bacdive"],"kinds":["carbon source"],"citation":"BacDive strain 140774 (Reimer LC et al., BacDive 2022, NAR); https://bacdive.dsmz.de/strain/140774"},{"substrate":"malate","exchange":"EX_mal__D_e","category":"carbon","phenotype":"negative","n_strains":1,"n_positive":0,"n_negative":1,"sources":["bacdive"],"kinds":["carbon source"],"citation":"BacDive strain 140774 (Reimer LC et al., BacDive 2022, NAR); https://bacdive.dsmz.de/strain/140774"},{"substrate":"phenylacetate","exchange":null,"category":"carbon","phenotype":"negative","n_strains":1,"n_positive":0,"n_negative":1,"sources":["bacdive"],"kinds":["carbon source"],"citation":"BacDive strain 140774 (Reimer LC et al., BacDive 2022, NAR); https://bacdive.dsmz.de/strain/140774"},{"substrate":"potassium gluconate","exchange":null,"category":"carbon","phenotype":"negative","n_strains":1,"n_positive":0,"n_negative":1,"sources":["bacdive"],"kinds":["carbon source"],"citation":"BacDive strain 140774 (Reimer LC et al., BacDive 2022, NAR); https://bacdive.dsmz.de/strain/140774"},{"substrate":"sodium citrate","exchange":null,"category":"carbon","phenotype":"negative","n_strains":1,"n_positive":0,"n_negative":1,"sources":["bacdive"],"kinds":["carbon source"],"citation":"BacDive strain 140774 (Reimer LC et al., BacDive 2022, NAR); https://bacdive.dsmz.de/strain/140774"},{"substrate":"gelatin","exchange":null,"category":"carbon","phenotype":"negative","n_strains":1,"n_positive":0,"n_negative":1,"sources":["bacdive"],"kinds":["hydrolysis"],"citation":"BacDive strain 140774 (Reimer LC et al., BacDive 2022, NAR); https://bacdive.dsmz.de/strain/140774"},{"substrate":"esculin","exchange":"EX_escul_e","category":"carbon","phenotype":"positive","n_strains":1,"n_positive":1,"n_negative":0,"sources":["bacdive"],"kinds":["hydrolysis"],"citation":"BacDive strain 140774 (Reimer LC et al., BacDive 2022, NAR); https://bacdive.dsmz.de/strain/140774"},{"substrate":"L-tyrosine","exchange":"EX_tyr__L_e","category":"carbon","phenotype":"positive","n_strains":1,"n_positive":1,"n_negative":0,"sources":["bacdive"],"kinds":["hydrolysis"],"citation":"BacDive strain 140774 (Reimer LC et al., BacDive 2022, NAR); https://bacdive.dsmz.de/strain/140774"},{"substrate":"tween 40","exchange":null,"category":"carbon","phenotype":"positive","n_strains":1,"n_positive":1,"n_negative":0,"sources":["bacdive"],"kinds":["hydrolysis"],"citation":"BacDive strain 140774 (Reimer LC et al., BacDive 2022, NAR); https://bacdive.dsmz.de/strain/140774"},{"substrate":"tween 80","exchange":null,"category":"carbon","phenotype":"positive","n_strains":1,"n_positive":1,"n_negative":0,"sources":["bacdive"],"kinds":["hydrolysis"],"citation":"BacDive strain 140774 (Reimer LC et al., BacDive 2022, NAR); https://bacdive.dsmz.de/strain/140774"},{"substrate":"nitrate","exchange":"EX_no3_e","category":"carbon","phenotype":"positive","n_strains":1,"n_positive":1,"n_negative":0,"sources":["bacdive"],"kinds":["reduction"],"citation":"BacDive strain 140774 (Reimer LC et al., BacDive 2022, NAR); https://bacdive.dsmz.de/strain/140774"}]}