{"species":"Thermomonospora echinospora","superkingdom":"Bacteria","n_records":0,"n_mu":0,"n_phenotypes":7,"growth_records":[],"phenotypes":[{"substrate":"gelatin","exchange":null,"category":"carbon","phenotype":"negative","n_strains":1,"n_positive":0,"n_negative":1,"sources":["bacdive"],"kinds":["hydrolysis"],"citation":"BacDive strain 16965 (Reimer LC et al., BacDive 2022, NAR); https://bacdive.dsmz.de/strain/16965"},{"substrate":"tryptophan","exchange":"EX_trp__L_e","category":"carbon","phenotype":"negative","n_strains":1,"n_positive":0,"n_negative":1,"sources":["bacdive"],"kinds":["energy source"],"citation":"BacDive strain 16965 (Reimer LC et al., BacDive 2022, NAR); https://bacdive.dsmz.de/strain/16965"},{"substrate":"urea","exchange":"EX_urea_e","category":"carbon","phenotype":"negative","n_strains":1,"n_positive":0,"n_negative":1,"sources":["bacdive"],"kinds":["hydrolysis"],"citation":"BacDive strain 16965 (Reimer LC et al., BacDive 2022, NAR); https://bacdive.dsmz.de/strain/16965"},{"substrate":"citrate","exchange":"EX_cit_e","category":"carbon","phenotype":"negative","n_strains":1,"n_positive":0,"n_negative":1,"sources":["bacdive"],"kinds":["assimilation"],"citation":"BacDive strain 16965 (Reimer LC et al., BacDive 2022, NAR); https://bacdive.dsmz.de/strain/16965"},{"substrate":"ornithine","exchange":"EX_orn__D_e","category":"carbon","phenotype":"negative","n_strains":1,"n_positive":0,"n_negative":1,"sources":["bacdive"],"kinds":["degradation"],"citation":"BacDive strain 16965 (Reimer LC et al., BacDive 2022, NAR); https://bacdive.dsmz.de/strain/16965"},{"substrate":"lysine","exchange":"EX_lys__L_e","category":"carbon","phenotype":"negative","n_strains":1,"n_positive":0,"n_negative":1,"sources":["bacdive"],"kinds":["degradation"],"citation":"BacDive strain 16965 (Reimer LC et al., BacDive 2022, NAR); https://bacdive.dsmz.de/strain/16965"},{"substrate":"arginine","exchange":"EX_arg__L_e","category":"carbon","phenotype":"negative","n_strains":1,"n_positive":0,"n_negative":1,"sources":["bacdive"],"kinds":["hydrolysis"],"citation":"BacDive strain 16965 (Reimer LC et al., BacDive 2022, NAR); https://bacdive.dsmz.de/strain/16965"}],"derived":{"n_substrates_positive":0,"n_substrates_negative":7,"utilizable_exchanges":[]}}