{"species":"Veillonella infantium","superkingdom":"Bacteria","n_records":0,"n_mu":0,"n_phenotypes":2,"growth_records":[],"phenotypes":[{"substrate":"lactate","exchange":"EX_lac__D_e","category":"carbon","phenotype":"positive","n_strains":1,"n_positive":1,"n_negative":0,"sources":["bacdive"],"kinds":["fermentation"],"citation":"BacDive strain 158785 (Reimer LC et al., BacDive 2022, NAR); https://bacdive.dsmz.de/strain/158785"},{"substrate":"nitrate","exchange":"EX_no3_e","category":"carbon","phenotype":"positive","n_strains":1,"n_positive":1,"n_negative":0,"sources":["bacdive"],"kinds":["reduction"],"citation":"BacDive strain 158785 (Reimer LC et al., BacDive 2022, NAR); https://bacdive.dsmz.de/strain/158785"}]}